doc_builder/__init__.py
doc_builder/autodoc.py
doc_builder/build_doc.py
doc_builder/convert_md_to_mdx.py
doc_builder/convert_rst_to_mdx.py
doc_builder/convert_to_notebook.py
doc_builder/external.py
doc_builder/frontmatter_node.py
doc_builder/style_doc.py
doc_builder/utils.py
doc_builder/commands/__init__.py
doc_builder/commands/build.py
doc_builder/commands/convert_doc_file.py
doc_builder/commands/doc_builder_cli.py
doc_builder/commands/notebook_to_mdx.py
doc_builder/commands/preview.py
doc_builder/commands/push.py
doc_builder/commands/style.py
hf_doc_builder-0.4.0.dist-info/LICENSE
hf_doc_builder-0.4.0.dist-info/METADATA
hf_doc_builder-0.4.0.dist-info/WHEEL
hf_doc_builder-0.4.0.dist-info/entry_points.txt
hf_doc_builder-0.4.0.dist-info/top_level.txt
hf_doc_builder-0.4.0.dist-info/RECORD
